helios/__init__.py
helios/defaults.py
helios/helios.py
helios/helios_test_trace.py
helios/py.typed
helios/sampler.py
helios/utils.py
helios/version.py
helios/aiosmtplib_instrumentation/__init__.py
helios/aiosmtplib_instrumentation/src/__init__.py
helios/aiosmtplib_instrumentation/src/aiosmtplib/__init__.py
helios/aiosmtplib_instrumentation/src/aiosmtplib/package.py
helios/base/__init__.py
helios/base/span_attributes.py
helios/base/data_obfuscator/__init__.py
helios/base/data_obfuscator/base_data_obfuscator.py
helios/base/data_obfuscator/redis_data_obfuscator.py
helios/base/span_attribute_dropper/__init__.py
helios/base/tracing/__init__.py
helios/base/tracing/suppress_tracing.py
helios/base/tracing/export/__init__.py
helios/base/tracing/export/conditional_span_processor.py
helios/base/tracing/export/fork_process_otlp_span_exporter.py
helios/base/tracing/export/hooked_batch_span_processor.py
helios/base/tracing/export/utils.py
helios/instrumentation/__init__.py
helios/instrumentation/aio_pika.py
helios/instrumentation/aiohttp.py
helios/instrumentation/aiosmtplib.py
helios/instrumentation/aws_lambda.py
helios/instrumentation/base.py
helios/instrumentation/base_http_instrumentor.py
helios/instrumentation/confluent_kafka.py
helios/instrumentation/django.py
helios/instrumentation/elasticsearch.py
helios/instrumentation/fastapi.py
helios/instrumentation/flask.py
helios/instrumentation/grpc.py
helios/instrumentation/helios_asgi_middleware.py
helios/instrumentation/httpx.py
helios/instrumentation/kafka.py
helios/instrumentation/logging.py
helios/instrumentation/pika.py
helios/instrumentation/psycopg2.py
helios/instrumentation/pymongo.py
helios/instrumentation/pyspark.py
helios/instrumentation/raven.py
helios/instrumentation/redis.py
helios/instrumentation/requests.py
helios/instrumentation/sentry.py
helios/instrumentation/starlette.py
helios/instrumentation/tornado.py
helios/instrumentation/urllib.py
helios/instrumentation/urllib3.py
helios_opentelemetry_sdk-1.0.102.dist-info/LICENSE
helios_opentelemetry_sdk-1.0.102.dist-info/METADATA
helios_opentelemetry_sdk-1.0.102.dist-info/WHEEL
helios_opentelemetry_sdk-1.0.102.dist-info/entry_points.txt
helios_opentelemetry_sdk-1.0.102.dist-info/top_level.txt
helios_opentelemetry_sdk-1.0.102.dist-info/RECORD
