Metadata-Version: 2.1
Name: helios-opentelemetry-sdk
Version: 1.0.102
Summary: Helios OpenTelemetry SDK
Home-page: https://docs.gethelios.dev/docs/python
Author: Helios
Author-email: support@gethelios.dev
License: Apache License 2.0
Keywords: helios,heliosphere,microservices,tracing,distributed-tracing,debugging,testing
Classifier: Intended Audience :: Developers
Classifier: Operating System :: OS Independent
Classifier: Programming Language :: Python
Classifier: Programming Language :: Python :: 3
Classifier: Programming Language :: Python :: 3.7
Classifier: Programming Language :: Python :: 3.8
Classifier: Programming Language :: Python :: 3.9
Classifier: Programming Language :: Python :: 3.10
Classifier: Framework :: Pytest
Classifier: Topic :: Software Development :: Libraries
Classifier: Topic :: Software Development :: Libraries :: Python Modules
Classifier: Typing :: Typed
License-File: LICENSE
Requires-Dist: autowrapt ==1.0
Requires-Dist: jsonpath-ng ==1.5.3
Requires-Dist: opentelemetry-api ==1.22.0
Requires-Dist: opentelemetry-exporter-otlp-proto-http ==1.22.0
Requires-Dist: opentelemetry-instrumentation-aio-pika ==0.43b0
Requires-Dist: opentelemetry-instrumentation-aiohttp-client ==0.43b0
Requires-Dist: opentelemetry-instrumentation-aiopg ==0.43b0
Requires-Dist: opentelemetry-instrumentation-asyncpg ==0.43b0
Requires-Dist: opentelemetry-instrumentation-aws-lambda ==0.43b0
Requires-Dist: opentelemetry-instrumentation-boto ==0.43b0
Requires-Dist: opentelemetry-instrumentation-botocore ==0.43b0
Requires-Dist: opentelemetry-instrumentation-celery ==0.43b0
Requires-Dist: opentelemetry-instrumentation-confluent-kafka ==0.43b0
Requires-Dist: opentelemetry-instrumentation-django ==0.43b0
Requires-Dist: opentelemetry-instrumentation-elasticsearch ==0.43b0
Requires-Dist: opentelemetry-instrumentation-fastapi ==0.43b0
Requires-Dist: opentelemetry-instrumentation-flask ==0.43b0
Requires-Dist: opentelemetry-instrumentation-grpc ==0.43b0
Requires-Dist: opentelemetry-instrumentation-httpx ==0.43b0
Requires-Dist: opentelemetry-instrumentation-logging ==0.43b0
Requires-Dist: opentelemetry-instrumentation-mysql ==0.43b0
Requires-Dist: opentelemetry-instrumentation-pika ==0.43b0
Requires-Dist: opentelemetry-instrumentation-psycopg2 ==0.43b0
Requires-Dist: opentelemetry-instrumentation-pymemcache ==0.43b0
Requires-Dist: opentelemetry-instrumentation-pymongo ==0.43b0
Requires-Dist: opentelemetry-instrumentation-pymysql ==0.43b0
Requires-Dist: opentelemetry-instrumentation-redis ==0.43b0
Requires-Dist: opentelemetry-instrumentation-requests ==0.43b0
Requires-Dist: opentelemetry-instrumentation-sqlalchemy ==0.43b0
Requires-Dist: opentelemetry-instrumentation-sqlite3 ==0.43b0
Requires-Dist: opentelemetry-instrumentation-starlette ==0.43b0
Requires-Dist: opentelemetry-instrumentation-tornado ==0.43b0
Requires-Dist: opentelemetry-instrumentation-urllib ==0.43b0
Requires-Dist: opentelemetry-instrumentation-urllib3 ==0.43b0
Requires-Dist: opentelemetry-instrumentation-system-metrics ==0.43b0
Requires-Dist: opentelemetry-instrumentation ==0.43b0
Requires-Dist: opentelemetry-sdk ==1.22.0
Requires-Dist: requests ~=2.22
Requires-Dist: protobuf !=3.20.0,!=3.20.1,<5.0,>=3.19
